ctapipe/__init__.py
ctapipe/_version.py
ctapipe/atmosphere.py
ctapipe/compat.py
ctapipe/conftest.py
ctapipe/containers.py
ctapipe/exceptions.py
ctapipe/fitting.py
ctapipe/time.py
ctapipe/version.py
ctapipe/calib/__init__.py
ctapipe/calib/camera/__init__.py
ctapipe/calib/camera/calibrator.py
ctapipe/calib/camera/gainselection.py
ctapipe/calib/camera/tests/__init__.py
ctapipe/calib/camera/tests/test_calibrator.py
ctapipe/calib/camera/tests/test_gainselection.py
ctapipe/calib/tests/__init__.py
ctapipe/coordinates/__init__.py
ctapipe/coordinates/camera_frame.py
ctapipe/coordinates/ground_frames.py
ctapipe/coordinates/impact_distance.py
ctapipe/coordinates/nominal_frame.py
ctapipe/coordinates/representation.py
ctapipe/coordinates/telescope_frame.py
ctapipe/coordinates/utils.py
ctapipe/coordinates/tests/__init__.py
ctapipe/coordinates/tests/test_coordinates.py
ctapipe/coordinates/tests/test_engineering_frame.py
ctapipe/coordinates/tests/test_ground_frame.py
ctapipe/coordinates/tests/test_impact_distance.py
ctapipe/coordinates/tests/test_nominal_frame.py
ctapipe/coordinates/tests/test_roundtrip.py
ctapipe/coordinates/tests/test_telescope_frame.py
ctapipe/coordinates/tests/test_utils.py
ctapipe/core/__init__.py
ctapipe/core/component.py
ctapipe/core/container.py
ctapipe/core/env.py
ctapipe/core/expression_engine.py
ctapipe/core/feature_generator.py
ctapipe/core/logging.py
ctapipe/core/plugins.py
ctapipe/core/provenance.py
ctapipe/core/qualityquery.py
ctapipe/core/support.py
ctapipe/core/telescope_component.py
ctapipe/core/tool.py
ctapipe/core/traits.py
ctapipe/core/tests/__init__.py
ctapipe/core/tests/test_component.py
ctapipe/core/tests/test_container.py
ctapipe/core/tests/test_expression_engine.py
ctapipe/core/tests/test_feature_generator.py
ctapipe/core/tests/test_logging.py
ctapipe/core/tests/test_provenance.py
ctapipe/core/tests/test_qualityquery.py
ctapipe/core/tests/test_run_tool.py
ctapipe/core/tests/test_telescope_component.py
ctapipe/core/tests/test_tool.py
ctapipe-0.29.0.dist-info/licenses/AUTHORS
ctapipe-0.29.0.dist-info/licenses/LICENSE
ctapipe-0.29.0.dist-info/METADATA
ctapipe-0.29.0.dist-info/WHEEL
ctapipe-0.29.0.dist-info/entry_points.txt
ctapipe-0.29.0.dist-info/top_level.txt
ctapipe-0.29.0.dist-info/RECORD
