Metadata-Version: 2.4
Name: ctapipe
Version: 0.29.0
Summary: Event reconstruction framework for Imaging Atmospheric Cherenkov Telescopes developed for CTAO.
Author: ctapipe developers
Maintainer-email: Karl Kosack <karl.kosack@cea.fr>, Maximilian Linhoff <maximilian.linhoff@tu-dortmund.de>
License-Expression: BSD-3-Clause
Project-URL: repository, https://github.com/cta-observatory/ctapipe/
Project-URL: documentation, https://ctapipe.readthedocs.io/
Classifier: Intended Audience :: Science/Research
Classifier: Programming Language :: Python :: 3
Classifier: Programming Language :: Python :: 3.12
Classifier: Programming Language :: Python :: 3.13
Classifier: Programming Language :: Python :: 3.14
Classifier: Programming Language :: Python :: Implementation :: CPython
Classifier: Topic :: Scientific/Engineering :: Astronomy
Classifier: Development Status :: 3 - Alpha
Requires-Python: >=3.12
License-File: LICENSE
License-File: AUTHORS
Requires-Dist: astropy<8.0.0,>=6.1
Requires-Dist: docutils
Requires-Dist: joblib
Requires-Dist: numba>=0.59.0
Requires-Dist: numpy<3.0.0,>=1.26
Requires-Dist: packaging
Requires-Dist: psutil
Requires-Dist: pyyaml>=5.1
Requires-Dist: requests
Requires-Dist: scikit-learn!=1.4.0
Requires-Dist: scipy~=1.15
Requires-Dist: tables~=3.4
Requires-Dist: tqdm>=4.32
Requires-Dist: traitlets~=5.6
Provides-Extra: eventio
Requires-Dist: eventio<3.0.0,>=1.9.1; extra == "eventio"
Provides-Extra: all
Requires-Dist: bokeh~=3.0; extra == "all"
Requires-Dist: ctapipe[eventio]; extra == "all"
Requires-Dist: iminuit>=2; extra == "all"
Requires-Dist: matplotlib~=3.0; extra == "all"
Requires-Dist: pyirf~=0.13.0; extra == "all"
Provides-Extra: tests
Requires-Dist: ctapipe[eventio]; extra == "tests"
Requires-Dist: h5py; extra == "tests"
Requires-Dist: pandas; extra == "tests"
Requires-Dist: pytest>=7.0; extra == "tests"
Requires-Dist: pytest-cov; extra == "tests"
Requires-Dist: pytest-xdist; extra == "tests"
Requires-Dist: pytest_astropy_header; extra == "tests"
Requires-Dist: tomli; extra == "tests"
Requires-Dist: astroquery; extra == "tests"
Provides-Extra: docs
Requires-Dist: ctapipe[all]; extra == "docs"
Requires-Dist: ffmpeg-python; extra == "docs"
Requires-Dist: graphviz; extra == "docs"
Requires-Dist: ipython; extra == "docs"
Requires-Dist: jupyter; extra == "docs"
Requires-Dist: nbsphinx; extra == "docs"
Requires-Dist: notebook; extra == "docs"
Requires-Dist: numpydoc; extra == "docs"
Requires-Dist: pandas; extra == "docs"
Requires-Dist: pydata_sphinx_theme; extra == "docs"
Requires-Dist: pypandoc; extra == "docs"
Requires-Dist: sphinx; extra == "docs"
Requires-Dist: sphinx-design; extra == "docs"
Requires-Dist: sphinx-gallery>=0.16.0; extra == "docs"
Requires-Dist: sphinx_automodapi; extra == "docs"
Requires-Dist: sphinxcontrib-bibtex; extra == "docs"
Requires-Dist: sphinx-changelog; extra == "docs"
Provides-Extra: dev
Requires-Dist: ctapipe[all,docs,tests]; extra == "dev"
Requires-Dist: pre-commit; extra == "dev"
Requires-Dist: setuptools_scm[toml]; extra == "dev"
Dynamic: license-file
